pleom_apitoolbox/__init__.py
pleom_apitoolbox/api_toolbox.py
pleom_apitoolbox/types.py
pleom_apitoolbox/user.py
pleom_apitoolbox/services/__init__.py
pleom_apitoolbox/services/service_downloader.py
pleom_apitoolbox/services/service_manager.py
pleom_apitoolbox-1.0.2.dist-info/METADATA
pleom_apitoolbox-1.0.2.dist-info/WHEEL
pleom_apitoolbox-1.0.2.dist-info/top_level.txt
pleom_apitoolbox-1.0.2.dist-info/RECORD
