Metadata-Version: 2.4
Name: pleom-apitoolbox
Version: 1.0.2
Summary: Stateless API Mapping Context for LLM Tooling - Python SDK
Author-email: Royce Arockiasamy <royce@pleom.com>
Maintainer-email: Royce Arockiasamy <royce@pleom.com>
Project-URL: Homepage, https://apitoolbox.dev
Project-URL: Repository, https://github.com/pleom/apitoolbox
Project-URL: Bug Tracker, https://github.com/pleom/apitoolbox/issues
Keywords: api,sdk,python,tools,llm,ai,async
Classifier: Development Status :: 4 - Beta
Classifier: Intended Audience :: Developers
Classifier: License :: OSI Approved :: MIT License
Classifier: Operating System :: OS Independent
Classifier: Programming Language :: Python :: 3
Classifier: Programming Language :: Python :: 3.8
Classifier: Programming Language :: Python :: 3.9
Classifier: Programming Language :: Python :: 3.10
Classifier: Programming Language :: Python :: 3.11
Classifier: Programming Language :: Python :: 3.12
Classifier: Topic :: Software Development :: Libraries :: Python Modules
Classifier: Topic :: Internet :: WWW/HTTP :: Dynamic Content
Classifier: Topic :: Software Development :: Libraries :: Application Frameworks
Requires-Python: >=3.8
Requires-Dist: aiohttp>=3.8.0
Provides-Extra: dev
Requires-Dist: pytest>=7.0.0; extra == "dev"
Requires-Dist: pytest-asyncio>=0.20.0; extra == "dev"
Requires-Dist: pytest-cov>=4.0.0; extra == "dev"
Requires-Dist: black>=22.0.0; extra == "dev"
Requires-Dist: isort>=5.10.0; extra == "dev"
Requires-Dist: mypy>=1.0.0; extra == "dev"
Requires-Dist: flake8>=5.0.0; extra == "dev"
